plain/scan/CHANGELOG.md
plain/scan/README.md
plain/scan/__init__.py
plain/scan/cli.py
plain/scan/entrypoints.py
plain/scan/metadata.py
plain/scan/output.py
plain/scan/results.py
plain/scan/scanner.py
plain/scan/audits/__init__.py
plain/scan/audits/base.py
plain/scan/audits/content_type_options.py
plain/scan/audits/cookies.py
plain/scan/audits/cors.py
plain/scan/audits/csp.py
plain/scan/audits/frame_options.py
plain/scan/audits/hsts.py
plain/scan/audits/redirects.py
plain/scan/audits/referrer_policy.py
plain/scan/audits/status_code.py
plain/scan/audits/tls.py
plain_scan-0.5.1.dist-info/METADATA
plain_scan-0.5.1.dist-info/WHEEL
plain_scan-0.5.1.dist-info/entry_points.txt
plain_scan-0.5.1.dist-info/licenses/LICENSE
plain_scan-0.5.1.dist-info/RECORD
