Metadata-Version: 2.4
Name: plain.scan
Version: 0.5.1
Summary: Remotely test for production best practices.
Author-email: Dave Gaeddert <dave.gaeddert@dropseed.dev>
License-Expression: BSD-3-Clause
License-File: LICENSE
Requires-Python: >=3.13
Requires-Dist: plain<1.0.0
Requires-Dist: requests
